sir_Bychko_serializer/__init__.py
sir_Bychko_serializer/constants.py
sir_Bychko_serializer/json_serializer.py
sir_Bychko_serializer/serialiser.py
sir_Bychko_serializer/serializer_zavod.py
sir_Bychko_serializer/xml_serializer.py
sir_Bychko_serializer-0.1.0.dist-info/METADATA
sir_Bychko_serializer-0.1.0.dist-info/WHEEL
sir_Bychko_serializer-0.1.0.dist-info/top_level.txt
sir_Bychko_serializer-0.1.0.dist-info/RECORD
