Metadata-Version: 2.1
Name: sir-Bychko-serializer
Version: 0.1.0
Summary: somme serialization
Home-page: UNKNOWN
Author: Sir Bychko Vassiliy
Author-email: vasa060504@mail.ru
License: MIT
Platform: UNKNOWN
Classifier: Intended Audience :: Developers
Classifier: License :: OSI Approved :: MIT License
Classifier: Programming Language :: Python :: 3.10
Classifier: Operating System :: OS Independent
Requires-Dist: regex
